{
  "version": "1.0",
  "timestamp": "2026-03-30T06:00:00Z",
  "phase": "post-milestone",
  "phase_name": "session 23 final — proof wall identified, prolate overlap next",
  "status": "paused",
  "next_action": "SESSION 24: Compute prolate overlap <xi_lambda, k_lambda> using actual prolate eigenfunctions h_{0,lambda}, h_{4,lambda} at higher lambda values. If overlap -> 1, the educated guess becomes a verifiable conjecture with explicit constants. This is the furthest anyone can go computationally without new analytic ideas.",
  "context_notes": "The Mellin/Fourier gap is intrinsic: explicit formula controls xi_tilde(rho) ~ eps_N ~ 10^{-2.3L}, but xi_hat(gamma) ~ 10^{-18} (41 orders larger). Bridging them = proving prolate concentration = proving RH. Scripts: connes_attack.py, connes_proof_checks.py, connes_G_test.py. Python: /c/Python313/python.exe, mp.dps=100."
}
